task2/f1_fsm.sv
module f1_fsm (
    input logic                     clk,    // clock
    input logic                     rst,    // reset
    input logic                     en,     // enable 
    output logic [7:0]              data_out    // output 
);

    // define our states
    typedef enum {S0, S1, S2, S3, S4, S5, S6, S7, S8}   F1_states;
    F1_states   current_state, next_state;

    // state registers
    always_ff @ (posedge clk, posedge rst)
        if (rst)        current_state <= S0;
        else if (en)    current_state <= next_state;

    // next state logic block
    always_comb
        case(current_state)
            S0:         next_state = S1;
            S1:         next_state = S2;
            S2:         next_state = S3;
            S3:         next_state = S4;
            S4:         next_state = S5;
            S5:         next_state = S6;
            S6:         next_state = S7;
            S7:         next_state = S8;
            S8:         next_state = S0;
            default:    next_state = S0;
        endcase 
    
    // output logic 
    always_comb 
        case(current_state)
            S0:         data_out = 8'b0;
            S1:         data_out = 8'b1;
            S2:         data_out = 8'b11;
            S3:         data_out = 8'b111;
            S4:         data_out = 8'b1111;
            S5:         data_out = 8'b11111;
            S6:         data_out = 8'b111111;
            S7:         data_out = 8'b1111111;
            S8:         data_out = 8'b11111111;
            default:    data_out = 8'b0;
        endcase

endmodule

task3/clktick.sv
module clktick #(         // module used to generate a pulse every N+1 rising eddge of clock cycles 
	parameter WIDTH = 6    // using parameter to make it adaptable
)(
  // interface signals
  input  logic             clk,      // clock 
  input  logic             rst,      // reset
  input  logic             en,       // enable signal
  input  logic [WIDTH-1:0] N,     	 // clock divided by N+1, for Dell, it is 53 decimal
  output logic  		       tick      // tick output
);

logic [WIDTH-1:0] count;              // internal counter which will count down. Count value goes from N to 0, hence the N+1 clock cycles for each tick

always_ff @ (posedge clk, posedge rst)             // flipflop, hence a state machine, the value of the clock tick and the count will be updated here after every clock cycle
    if (rst) begin
        tick <= 1'b0;                 // initially set the tick to zero
        count <= N;                   // and counter has value N
        end
    else if (en) begin                // enable signal to activate the block
	    if (count == 0) begin           // when count is 0, produce a pulse lasting for a single clock cycle and reset the value of count to N
		    tick <= 1'b1;
		    count <= N;
	        end
	    else begin                      // otherwise return 0 for the pulse and keep counting down on every posedge
		    tick <= 1'b0;
		    count <= count - 1'b1;
	        end
        end
endmodule

task3/f1_fsm_1s.sv
module f1_fsm_1s (
    input logic                 clk,    // clock
    input logic                 rst,    // reset signal
    output logic [7:0]          data_out    // output signal
);

    logic                       tick;   // interconnecting wire between clktick and f1_fsm

clktick myClktick (
    .clk (clk),
    .rst (rst),
    .en (1'b1),
    .N (6'd53),
    .tick (tick)
);

f1_fsm myF1_fsm(
    .clk (clk),
    .rst (rst),
    .en (tick),
    .data_out (data_out)
);

endmodule

task3/f1_fsm_1s.vcd
$version Generated by VerilatedVcd $end
$date Wed Dec 14 14:16:42 2022 $end
$timescale 1ps $end

 $scope module TOP $end
  $var wire  1 ' clk $end
  $var wire  8 ) data_out [7:0] $end
  $var wire  1 ( rst $end
  $scope module f1_fsm_1s $end
   $var wire  1 ' clk $end
   $var wire  8 ) data_out [7:0] $end
   $var wire  1 ( rst $end
   $var wire  1 # tick $end
   $scope module myClktick $end
    $var wire  6 , N [5:0] $end
    $var wire 32 * WIDTH [31:0] $end
    $var wire  1 ' clk $end
    $var wire  6 $ count [5:0] $end
    $var wire  1 + en $end
    $var wire  1 ( rst $end
    $var wire  1 # tick $end
   $upscope $end
   $scope module myF1_fsm $end
    $var wire  1 ' clk $end
    $var wire 32 % current_state [31:0] $end
    $var wire  8 ) data_out [7:0] $end
    $var wire  1 # en $end
    $var wire 32 & next_state [31:0] $end
    $var wire  1 ( rst $end
   $upscope $end
  $upscope $end
 $upscope $end
$enddefinitions $end


#0
0#
b000000 $
b00000000000000000000000000000000 %
b00000000000000000000000000000001 &
1'
1(
b00000000 )
b00000000000000000000000000000110 *
1+
b110101 ,
#1
0'
#2
b110101 $
1'
#3
0'
#4
1'
#5
0'
#6
1'
0(
#7
0'
#8
b110100 $
1'
#9
0'
#10
b110011 $
1'
#11
0'
#12
b110010 $
1'
#13
0'
#14
b110001 $
1'
#15
0'
#16
b110000 $
1'
#17
0'
#18
b101111 $
1'
#19
0'
#20
b101110 $
1'
#21
0'
#22
b101101 $
1'
#23
0'
#24
b101100 $
1'
#25
0'
#26
b101011 $
1'
#27
0'
#28
b101010 $
1'
#29
0'
#30
b101001 $
1'
#31
0'
#32
b101000 $
1'
#33
0'
#34
b100111 $
1'
#35
0'
#36
b100110 $
1'
#37
0'
#38
b100101 $
1'
#39
0'
#40
b100100 $
1'
#41
0'
#42
b100011 $
1'
#43
0'
#44
b100010 $
1'
#45
0'
#46
b100001 $
1'
#47
0'
#48
b100000 $
1'
#49
0'
#50
b011111 $
1'
#51
0'
#52
b011110 $
1'
#53
0'
#54
b011101 $
1'
#55
0'
#56
b011100 $
1'
#57
0'
#58
b011011 $
1'
#59
0'
#60
b011010 $
1'
#61
0'
#62
b011001 $
1'
#63
0'
#64
b011000 $
1'
#65
0'
#66
b010111 $
1'
#67
0'
#68
b010110 $
1'
#69
0'
#70
b010101 $
1'
#71
0'
#72
b010100 $
1'
#73
0'
#74
b010011 $
1'
#75
0'
#76
b010010 $
1'
#77
0'
#78
b010001 $
1'
#79
0'
#80
b010000 $
1'
#81
0'
#82
b001111 $
1'
#83
0'
#84
b001110 $
1'
#85
0'
#86
b001101 $
1'
#87
0'
#88
b001100 $
1'
#89
0'
#90
b001011 $
1'
#91
0'
#92
b001010 $
1'
#93
0'
#94
b001001 $
1'
#95
0'
#96
b001000 $
1'
#97
0'
#98
b000111 $
1'
#99
0'
#100
b000110 $
1'
#101
0'
#102
b000101 $
1'
#103
0'
#104
b000100 $
1'
#105
0'
#106
b000011 $
1'
#107
0'
#108
b000010 $
1'
#109
0'
#110
b000001 $
1'
#111
0'
#112
b000000 $
1'
#113
0'
#114
1#
b110101 $
1'
#115
0'
#116
0#
b110100 $
b00000000000000000000000000000001 %
b00000000000000000000000000000010 &
1'
b00000001 )
#117
0'
#118
b110011 $
1'
#119
0'
#120
b110010 $
1'
#121
0'
#122
b110001 $
1'
#123
0'
#124
b110000 $
1'
#125
0'
#126
b101111 $
1'
#127
0'
#128
b101110 $
1'
#129
0'
#130
b101101 $
1'
#131
0'
#132
b101100 $
1'
#133
0'
#134
b101011 $
1'
#135
0'
#136
b101010 $
1'
#137
0'
#138
b101001 $
1'
#139
0'
#140
b101000 $
1'
#141
0'
#142
b100111 $
1'
#143
0'
#144
b100110 $
1'
#145
0'
#146
b100101 $
1'
#147
0'
#148
b100100 $
1'
#149
0'
#150
b100011 $
1'
#151
0'
#152
b100010 $
1'
#153
0'
#154
b100001 $
1'
#155
0'
#156
b100000 $
1'
#157
0'
#158
b011111 $
1'
#159
0'
#160
b011110 $
1'
#161
0'
#162
b011101 $
1'
#163
0'
#164
b011100 $
1'
#165
0'
#166
b011011 $
1'
#167
0'
#168
b011010 $
1'
#169
0'
#170
b011001 $
1'
#171
0'
#172
b011000 $
1'
#173
0'
#174
b010111 $
1'
#175
0'
#176
b010110 $
1'
#177
0'
#178
b010101 $
1'
#179
0'
#180
b010100 $
1'
#181
0'
#182
b010011 $
1'
#183
0'
#184
b010010 $
1'
#185
0'
#186
b010001 $
1'
#187
0'
#188
b010000 $
1'
#189
0'
#190
b001111 $
1'
#191
0'
#192
b001110 $
1'
#193
0'
#194
b001101 $
1'
#195
0'
#196
b001100 $
1'
#197
0'
#198
b001011 $
1'
#199
0'
#200
b001010 $
1'
#201
0'
#202
b001001 $
1'
#203
0'
#204
b001000 $
1'
#205
0'
#206
b000111 $
1'
#207
0'
#208
b000110 $
1'
#209
0'
#210
b000101 $
1'
#211
0'
#212
b000100 $
1'
#213
0'
#214
b000011 $
1'
#215
0'
#216
b000010 $
1'
#217
0'
#218
b000001 $
1'
#219
0'
#220
b000000 $
1'
#221
0'
#222
1#
b110101 $
1'
#223
0'
#224
0#
b110100 $
b00000000000000000000000000000010 %
b00000000000000000000000000000011 &
1'
b00000011 )
#225
0'
#226
b110011 $
1'
#227
0'
#228
b110010 $
1'
#229
0'
#230
b110001 $
1'
#231
0'
#232
b110000 $
1'
#233
0'
#234
b101111 $
1'
#235
0'
#236
b101110 $
1'
#237
0'
#238
b101101 $
1'
#239
0'
#240
b101100 $
1'
#241
0'
#242
b101011 $
1'
#243
0'
#244
b101010 $
1'
#245
0'
#246
b101001 $
1'
#247
0'
#248
b101000 $
1'
#249
0'
#250
b100111 $
1'
#251
0'
#252
b100110 $
1'
#253
0'
#254
b100101 $
1'
#255
0'
#256
b100100 $
1'
#257
0'
#258
b100011 $
1'
#259
0'
#260
b100010 $
1'
#261
0'
#262
b100001 $
1'
#263
0'
#264
b100000 $
1'
#265
0'
#266
b011111 $
1'
#267
0'
#268
b011110 $
1'
#269
0'
#270
b011101 $
1'
#271
0'
#272
b011100 $
1'
#273
0'
#274
b011011 $
1'
#275
0'
#276
b011010 $
1'
#277
0'
#278
b011001 $
1'
#279
0'
#280
b011000 $
1'
#281
0'
#282
b010111 $
1'
#283
0'
#284
b010110 $
1'
#285
0'
#286
b010101 $
1'
#287
0'
#288
b010100 $
1'
#289
0'
#290
b010011 $
1'
#291
0'
#292
b010010 $
1'
#293
0'
#294
b010001 $
1'
#295
0'
#296
b010000 $
1'
#297
0'
#298
b001111 $
1'
#299
0'
#300
b001110 $
1'
#301
0'
#302
b001101 $
1'
#303
0'
#304
b001100 $
1'
#305
0'
#306
b001011 $
1'
#307
0'
#308
b001010 $
1'
#309
0'
#310
b001001 $
1'
#311
0'
#312
b001000 $
1'
#313
0'
#314
b000111 $
1'
#315
0'
#316
b000110 $
1'
#317
0'
#318
b000101 $
1'
#319
0'
#320
b000100 $
1'
#321
0'
#322
b000011 $
1'
#323
0'
#324
b000010 $
1'
#325
0'
#326
b000001 $
1'
#327
0'
#328
b000000 $
1'
#329
0'
#330
1#
b110101 $
1'
#331
0'
#332
0#
b110100 $
b00000000000000000000000000000011 %
b00000000000000000000000000000100 &
1'
b00000111 )
#333
0'
#334
b110011 $
1'
#335
0'
#336
b110010 $
1'
#337
0'
#338
b110001 $
1'
#339
0'
#340
b110000 $
1'
#341
0'
#342
b101111 $
1'
#343
0'
#344
b101110 $
1'
#345
0'
#346
b101101 $
1'
#347
0'
#348
b101100 $
1'
#349
0'
#350
b101011 $
1'
#351
0'
#352
b101010 $
1'
#353
0'
#354
b101001 $
1'
#355
0'
#356
b101000 $
1'
#357
0'
#358
b100111 $
1'
#359
0'
#360
b100110 $
1'
#361
0'
#362
b100101 $
1'
#363
0'
#364
b100100 $
1'
#365
0'
#366
b100011 $
1'
#367
0'
#368
b100010 $
1'
#369
0'
#370
b100001 $
1'
#371
0'
#372
b100000 $
1'
#373
0'
#374
b011111 $
1'
#375
0'
#376
b011110 $
1'
#377
0'
#378
b011101 $
1'
#379
0'
#380
b011100 $
1'
#381
0'
#382
b011011 $
1'
#383
0'
#384
b011010 $
1'
#385
0'
#386
b011001 $
1'
#387
0'
#388
b011000 $
1'
#389
0'
#390
b010111 $
1'
#391
0'
#392
b010110 $
1'
#393
0'
#394
b010101 $
1'
#395
0'
#396
b010100 $
1'
#397
0'
#398
b010011 $
1'
#399
0'
#400
b010010 $
1'
#401
0'
#402
b010001 $
1'
#403
0'
#404
b010000 $
1'
#405
0'
#406
b001111 $
1'
#407
0'
#408
b001110 $
1'
#409
0'
#410
b001101 $
1'
#411
0'
#412
b001100 $
1'
#413
0'
#414
b001011 $
1'
#415
0'
#416
b001010 $
1'
#417
0'
#418
b001001 $
1'
#419
0'
#420
b001000 $
1'
#421
0'
#422
b000111 $
1'
#423
0'
#424
b000110 $
1'
#425
0'
#426
b000101 $
1'
#427
0'
#428
b000100 $
1'
#429
0'
#430
b000011 $
1'
#431
0'
#432
b000010 $
1'
#433
0'
#434
b000001 $
1'
#435
0'
#436
b000000 $
1'
#437
0'
#438
1#
b110101 $
1'
#439
0'
#440
0#
b110100 $
b00000000000000000000000000000100 %
b00000000000000000000000000000101 &
1'
b00001111 )
#441
0'
#442
b110011 $
1'
#443
0'
#444
b110010 $
1'
#445
0'
#446
b110001 $
1'
#447
0'
#448
b110000 $
1'
#449
0'
#450
b101111 $
1'
#451
0'
#452
b101110 $
1'
#453
0'
#454
b101101 $
1'
#455
0'
#456
b101100 $
1'
#457
0'
#458
b101011 $
1'
#459
0'
#460
b101010 $
1'
#461
0'
#462
b101001 $
1'
#463
0'
#464
b101000 $
1'
#465
0'
#466
b100111 $
1'
#467
0'
#468
b100110 $
1'
#469
0'
#470
b100101 $
1'
#471
0'
#472
b100100 $
1'
#473
0'
#474
b100011 $
1'
#475
0'
#476
b100010 $
1'
#477
0'
#478
b100001 $
1'
#479
0'
#480
b100000 $
1'
#481
0'
#482
b011111 $
1'
#483
0'
#484
b011110 $
1'
#485
0'
#486
b011101 $
1'
#487
0'
#488
b011100 $
1'
#489
0'
#490
b011011 $
1'
#491
0'
#492
b011010 $
1'
#493
0'
#494
b011001 $
1'
#495
0'
#496
b011000 $
1'
#497
0'
#498
b010111 $
1'
#499
0'
#500
b010110 $
1'
#501
0'
#502
b010101 $
1'
#503
0'
#504
b010100 $
1'
#505
0'
#506
b010011 $
1'
#507
0'
#508
b010010 $
1'
#509
0'
#510
b010001 $
1'
#511
0'
#512
b010000 $
1'
#513
0'
#514
b001111 $
1'
#515
0'
#516
b001110 $
1'
#517
0'
#518
b001101 $
1'
#519
0'
#520
b001100 $
1'
#521
0'
#522
b001011 $
1'
#523
0'
#524
b001010 $
1'
#525
0'
#526
b001001 $
1'
#527
0'
#528
b001000 $
1'
#529
0'
#530
b000111 $
1'
#531
0'
#532
b000110 $
1'
#533
0'
#534
b000101 $
1'
#535
0'
#536
b000100 $
1'
#537
0'
#538
b000011 $
1'
#539
0'
#540
b000010 $
1'
#541
0'
#542
b000001 $
1'
#543
0'
#544
b000000 $
1'
#545
0'
#546
1#
b110101 $
1'
#547
0'
#548
0#
b110100 $
b00000000000000000000000000000101 %
b00000000000000000000000000000110 &
1'
b00011111 )
#549
0'
#550
b110011 $
1'
#551
0'
#552
b110010 $
1'
#553
0'
#554
b110001 $
1'
#555
0'
#556
b110000 $
1'
#557
0'
#558
b101111 $
1'
#559
0'
#560
b101110 $
1'
#561
0'
#562
b101101 $
1'
#563
0'
#564
b101100 $
1'
#565
0'
#566
b101011 $
1'
#567
0'
#568
b101010 $
1'
#569
0'
#570
b101001 $
1'
#571
0'
#572
b101000 $
1'
#573
0'
#574
b100111 $
1'
#575
0'
#576
b100110 $
1'
#577
0'
#578
b100101 $
1'
#579
0'
#580
b100100 $
1'
#581
0'
#582
b100011 $
1'
#583
0'
#584
b100010 $
1'
#585
0'
#586
b100001 $
1'
#587
0'
#588
b100000 $
1'
#589
0'
#590
b011111 $
1'
#591
0'
#592
b011110 $
1'
#593
0'
#594
b011101 $
1'
#595
0'
#596
b011100 $
1'
#597
0'
#598
b011011 $
1'
#599
0'
#600
b011010 $
1'
#601
0'
#602
b011001 $
1'
#603
0'
#604
b011000 $
1'
#605
0'
#606
b010111 $
1'
#607
0'
#608
b010110 $
1'
#609
0'
#610
b010101 $
1'
#611
0'
#612
b010100 $
1'
#613
0'
#614
b010011 $
1'
#615
0'
#616
b010010 $
1'
#617
0'
#618
b010001 $
1'
#619
0'
#620
b010000 $
1'
#621
0'
#622
b001111 $
1'
#623
0'
#624
b001110 $
1'
#625
0'
#626
b001101 $
1'
#627
0'
#628
b001100 $
1'
#629
0'
#630
b001011 $
1'
#631
0'
#632
b001010 $
1'
#633
0'
#634
b001001 $
1'
#635
0'
#636
b001000 $
1'
#637
0'
#638
b000111 $
1'
#639
0'
#640
b000110 $
1'
#641
0'
#642
b000101 $
1'
#643
0'
#644
b000100 $
1'
#645
0'
#646
b000011 $
1'
#647
0'
#648
b000010 $
1'
#649
0'
#650
b000001 $
1'
#651
0'
#652
b000000 $
1'
#653
0'
#654
1#
b110101 $
1'
#655
0'
#656
0#
b110100 $
b00000000000000000000000000000110 %
b00000000000000000000000000000111 &
1'
b00111111 )
#657
0'
#658
b110011 $
1'
#659
0'
#660
b110010 $
1'
#661
0'
#662
b110001 $
1'
#663
0'
#664
b110000 $
1'
#665
0'
#666
b101111 $
1'
#667
0'
#668
b101110 $
1'
#669
0'
#670
b101101 $
1'
#671
0'
#672
b101100 $
1'
#673
0'
#674
b101011 $
1'
#675
0'
#676
b101010 $
1'
#677
0'
#678
b101001 $
1'
#679
0'
#680
b101000 $
1'
#681
0'
#682
b100111 $
1'
#683
0'
#684
b100110 $
1'
#685
0'
#686
b100101 $
1'
#687
0'
#688
b100100 $
1'
#689
0'
#690
b100011 $
1'
#691
0'
#692
b100010 $
1'
#693
0'
#694
b100001 $
1'
#695
0'
#696
b100000 $
1'
#697
0'
#698
b011111 $
1'
#699
0'
#700
b011110 $
1'
#701
0'
#702
b011101 $
1'
#703
0'
#704
b011100 $
1'
#705
0'
#706
b011011 $
1'
#707
0'
#708
b011010 $
1'
#709
0'
#710
b011001 $
1'
#711
0'
#712
b011000 $
1'
#713
0'
#714
b010111 $
1'
#715
0'
#716
b010110 $
1'
#717
0'
#718
b010101 $
1'
#719
0'
#720
b010100 $
1'
#721
0'
#722
b010011 $
1'
#723
0'
#724
b010010 $
1'
#725
0'
#726
b010001 $
1'
#727
0'
#728
b010000 $
1'
#729
0'
#730
b001111 $
1'
#731
0'
#732
b001110 $
1'
#733
0'
#734
b001101 $
1'
#735
0'
#736
b001100 $
1'
#737
0'
#738
b001011 $
1'
#739
0'
#740
b001010 $
1'
#741
0'
#742
b001001 $
1'
#743
0'
#744
b001000 $
1'
#745
0'
#746
b000111 $
1'
#747
0'
#748
b000110 $
1'
#749
0'
#750
b000101 $
1'
#751
0'
#752
b000100 $
1'
#753
0'
#754
b000011 $
1'
#755
0'
#756
b000010 $
1'
#757
0'
#758
b000001 $
1'
#759
0'
#760
b000000 $
1'
#761
0'
#762
1#
b110101 $
1'
#763
0'
#764
0#
b110100 $
b00000000000000000000000000000111 %
b00000000000000000000000000001000 &
1'
b01111111 )
#765
0'
#766
b110011 $
1'
#767
0'
#768
b110010 $
1'
#769
0'
#770
b110001 $
1'
#771
0'
#772
b110000 $
1'
#773
0'
#774
b101111 $
1'
#775
0'
#776
b101110 $
1'
#777
0'
#778
b101101 $
1'
#779
0'
#780
b101100 $
1'
#781
0'
#782
b101011 $
1'
#783
0'
#784
b101010 $
1'
#785
0'
#786
b101001 $
1'
#787
0'
#788
b101000 $
1'
#789
0'
#790
b100111 $
1'
#791
0'
#792
b100110 $
1'
#793
0'
#794
b100101 $
1'
#795
0'
#796
b100100 $
1'
#797
0'
#798
b100011 $
1'
#799
0'
#800
b100010 $
1'
#801
0'
#802
b100001 $
1'
#803
0'
#804
b100000 $
1'
#805
0'
#806
b011111 $
1'
#807
0'
#808
b011110 $
1'
#809
0'
#810
b011101 $
1'
#811
0'
#812
b011100 $
1'
#813
0'
#814
b011011 $
1'
#815
0'
#816
b011010 $
1'
#817
0'
#818
b011001 $
1'
#819
0'
#820
b011000 $
1'
#821
0'
#822
b010111 $
1'
#823
0'
#824
b010110 $
1'
#825
0'
#826
b010101 $
1'
#827
0'
#828
b010100 $
1'
#829
0'
#830
b010011 $
1'
#831
0'
#832
b010010 $
1'
#833
0'
#834
b010001 $
1'
#835
0'
#836
b010000 $
1'
#837
0'
#838
b001111 $
1'
#839
0'
#840
b001110 $
1'
#841
0'
#842
b001101 $
1'
#843
0'
#844
b001100 $
1'
#845
0'
#846
b001011 $
1'
#847
0'
#848
b001010 $
1'
#849
0'
#850
b001001 $
1'
#851
0'
#852
b001000 $
1'
#853
0'
#854
b000111 $
1'
#855
0'
#856
b000110 $
1'
#857
0'
#858
b000101 $
1'
#859
0'
#860
b000100 $
1'
#861
0'
#862
b000011 $
1'
#863
0'
#864
b000010 $
1'
#865
0'
#866
b000001 $
1'
#867
0'
#868
b000000 $
1'
#869
0'
#870
1#
b110101 $
1'
#871
0'
#872
0#
b110100 $
b00000000000000000000000000001000 %
b00000000000000000000000000000000 &
1'
b11111111 )
#873
0'
#874
b110011 $
1'
#875
0'
#876
b110010 $
1'
#877
0'
#878
b110001 $
1'
#879
0'
#880
b110000 $
1'
#881
0'
#882
b101111 $
1'
#883
0'
#884
b101110 $
1'
#885
0'
#886
b101101 $
1'
#887
0'
#888
b101100 $
1'
#889
0'
#890
b101011 $
1'
#891
0'
#892
b101010 $
1'
#893
0'
#894
b101001 $
1'
#895
0'
#896
b101000 $
1'
#897
0'
#898
b100111 $
1'
#899
0'
#900
b100110 $
1'
#901
0'
#902
b100101 $
1'
#903
0'
#904
b100100 $
1'
#905
0'
#906
b100011 $
1'
#907
0'
#908
b100010 $
1'
#909
0'
#910
b100001 $
1'
#911
0'
#912
b100000 $
1'
#913
0'
#914
b011111 $
1'
#915
0'
#916
b011110 $
1'
#917
0'
#918
b011101 $
1'
#919
0'
#920
b011100 $
1'
#921
0'
#922
b011011 $
1'
#923
0'
#924
b011010 $
1'
#925
0'
#926
b011001 $
1'
#927
0'
#928
b011000 $
1'
#929
0'
#930
b010111 $
1'
#931
0'
#932
b010110 $
1'
#933
0'
#934
b010101 $
1'
#935
0'
#936
b010100 $
1'
#937
0'
#938
b010011 $
1'
#939
0'
#940
b010010 $
1'
#941
0'
#942
b010001 $
1'
#943
0'
#944
b010000 $
1'
#945
0'
#946
b001111 $
1'
#947
0'
#948
b001110 $
1'
#949
0'
#950
b001101 $
1'
#951
0'
#952
b001100 $
1'
#953
0'
#954
b001011 $
1'
#955
0'
#956
b001010 $
1'
#957
0'
#958
b001001 $
1'
#959
0'
#960
b001000 $
1'
#961
0'
#962
b000111 $
1'
#963
0'
#964
b000110 $
1'
#965
0'
#966
b000101 $
1'
#967
0'
#968
b000100 $
1'
#969
0'
#970
b000011 $
1'
#971
0'
#972
b000010 $
1'
#973
0'
#974
b000001 $
1'
#975
0'
#976
b000000 $
1'
#977
0'
#978
1#
b110101 $
1'
#979
0'
#980
0#
b110100 $
b00000000000000000000000000000000 %
b00000000000000000000000000000001 &
1'
b00000000 )
#981
0'
#982
b110011 $
1'
#983
0'
#984
b110010 $
1'
#985
0'
#986
b110001 $
1'
#987
0'
#988
b110000 $
1'
#989
0'
#990
b101111 $
1'
#991
0'
#992
b101110 $
1'
#993
0'
#994
b101101 $
1'
#995
0'
#996
b101100 $
1'
#997
0'
#998
b101011 $
1'
#999
0'
#1000
b101010 $
1'
#1001
0'
#1002
b101001 $
1'
#1003
0'
#1004
b101000 $
1'
#1005
0'
#1006
b100111 $
1'
#1007
0'
#1008
b100110 $
1'
#1009
0'
#1010
b100101 $
1'
#1011
0'
#1012
b100100 $
1'
#1013
0'
#1014
b100011 $
1'
#1015
0'
#1016
b100010 $
1'
#1017
0'
#1018
b100001 $
1'
#1019
0'
#1020
b100000 $
1'
#1021
0'
#1022
b011111 $
1'
#1023
0'
#1024
b011110 $
1'
#1025
0'
#1026
b011101 $
1'
#1027
0'
#1028
b011100 $
1'
#1029
0'
#1030
b011011 $
1'
#1031
0'
#1032
b011010 $
1'
#1033
0'
#1034
b011001 $
1'
#1035
0'
#1036
b011000 $
1'
#1037
0'
#1038
b010111 $
1'
#1039
0'
#1040
b010110 $
1'
#1041
0'
#1042
b010101 $
1'
#1043
0'
#1044
b010100 $
1'
#1045
0'
#1046
b010011 $
1'
#1047
0'
#1048
b010010 $
1'
#1049
0'
#1050
b010001 $
1'
#1051
0'
#1052
b010000 $
1'
#1053
0'
#1054
b001111 $
1'
#1055
0'
#1056
b001110 $
1'
#1057
0'
#1058
b001101 $
1'
#1059
0'
#1060
b001100 $
1'
#1061
0'
#1062
b001011 $
1'
#1063
0'
#1064
b001010 $
1'
#1065
0'
#1066
b001001 $
1'
#1067
0'
#1068
b001000 $
1'
#1069
0'
#1070
b000111 $
1'
#1071
0'
#1072
b000110 $
1'
#1073
0'
#1074
b000101 $
1'
#1075
0'
#1076
b000100 $
1'
#1077
0'
#1078
b000011 $
1'
#1079
0'
#1080
b000010 $
1'
#1081
0'
#1082
b000001 $
1'
#1083
0'
#1084
b000000 $
1'
#1085
0'
#1086
1#
b110101 $
1'
#1087
0'
#1088
0#
b110100 $
b00000000000000000000000000000001 %
b00000000000000000000000000000010 &
1'
b00000001 )
#1089
0'
#1090
b110011 $
1'
#1091
0'
#1092
b110010 $
1'
#1093
0'
#1094
b110001 $
1'
#1095
0'
#1096
b110000 $
1'
#1097
0'
#1098
b101111 $
1'
#1099
0'
#1100
b101110 $
1'
#1101
0'
#1102
b101101 $
1'
#1103
0'
#1104
b101100 $
1'
#1105
0'
#1106
b101011 $
1'
#1107
0'
#1108
b101010 $
1'
#1109
0'
#1110
b101001 $
1'
#1111
0'
#1112
b101000 $
1'
#1113
0'
#1114
b100111 $
1'
#1115
0'
#1116
b100110 $
1'
#1117
0'
#1118
b100101 $
1'
#1119
0'
#1120
b100100 $
1'
#1121
0'
#1122
b100011 $
1'
#1123
0'
#1124
b100010 $
1'
#1125
0'
#1126
b100001 $
1'
#1127
0'
#1128
b100000 $
1'
#1129
0'
#1130
b011111 $
1'
#1131
0'
#1132
b011110 $
1'
#1133
0'
#1134
b011101 $
1'
#1135
0'
#1136
b011100 $
1'
#1137
0'
#1138
b011011 $
1'
#1139
0'
#1140
b011010 $
1'
#1141
0'
#1142
b011001 $
1'
#1143
0'
#1144
b011000 $
1'
#1145
0'
#1146
b010111 $
1'
#1147
0'
#1148
b010110 $
1'
#1149
0'
#1150
b010101 $
1'
#1151
0'
#1152
b010100 $
1'
#1153
0'
#1154
b010011 $
1'
#1155
0'
#1156
b010010 $
1'
#1157
0'
#1158
b010001 $
1'
#1159
0'
#1160
b010000 $
1'
#1161
0'
#1162
b001111 $
1'
#1163
0'
#1164
b001110 $
1'
#1165
0'
#1166
b001101 $
1'
#1167
0'
#1168
b001100 $
1'
#1169
0'
#1170
b001011 $
1'
#1171
0'
#1172
b001010 $
1'
#1173
0'
#1174
b001001 $
1'
#1175
0'
#1176
b001000 $
1'
#1177
0'
#1178
b000111 $
1'
#1179
0'
#1180
b000110 $
1'
#1181
0'
#1182
b000101 $
1'
#1183
0'
#1184
b000100 $
1'
#1185
0'
#1186
b000011 $
1'
#1187
0'
#1188
b000010 $
1'
#1189
0'
#1190
b000001 $
1'
#1191
0'
#1192
b000000 $
1'
#1193
0'
#1194
1#
b110101 $
1'
#1195
0'
#1196
0#
b110100 $
b00000000000000000000000000000010 %
b00000000000000000000000000000011 &
1'
b00000011 )
#1197
0'
#1198
b110011 $
1'
#1199
0'
#1200
b110010 $
1'
#1201
0'
#1202
b110001 $
1'
#1203
0'
#1204
b110000 $
1'
#1205
0'
#1206
b101111 $
1'
#1207
0'
#1208
b101110 $
1'
#1209
0'
#1210
b101101 $
1'
#1211
0'
#1212
b101100 $
1'
#1213
0'
#1214
b101011 $
1'
#1215
0'
#1216
b101010 $
1'
#1217
0'
#1218
b101001 $
1'
#1219
0'
#1220
b101000 $
1'
#1221
0'
#1222
b100111 $
1'
#1223
0'
#1224
b100110 $
1'
#1225
0'
#1226
b100101 $
1'
#1227
0'
#1228
b100100 $
1'
#1229
0'
#1230
b100011 $
1'
#1231
0'
#1232
b100010 $
1'
#1233
0'
#1234
b100001 $
1'
#1235
0'
#1236
b100000 $
1'
#1237
0'
#1238
b011111 $
1'
#1239
0'
#1240
b011110 $
1'
#1241
0'
#1242
b011101 $
1'
#1243
0'
#1244
b011100 $
1'
#1245
0'
#1246
b011011 $
1'
#1247
0'
#1248
b011010 $
1'
#1249
0'
#1250
b011001 $
1'
#1251
0'
#1252
b011000 $
1'
#1253
0'
#1254
b010111 $
1'
#1255
0'
#1256
b010110 $
1'
#1257
0'
#1258
b010101 $
1'
#1259
0'
#1260
b010100 $
1'
#1261
0'
#1262
b010011 $
1'
#1263
0'
#1264
b010010 $
1'
#1265
0'
#1266
b010001 $
1'
#1267
0'
#1268
b010000 $
1'
#1269
0'
#1270
b001111 $
1'
#1271
0'
#1272
b001110 $
1'
#1273
0'
#1274
b001101 $
1'
#1275
0'
#1276
b001100 $
1'
#1277
0'
#1278
b001011 $
1'
#1279
0'
#1280
b001010 $
1'
#1281
0'
#1282
b001001 $
1'
#1283
0'
#1284
b001000 $
1'
#1285
0'
#1286
b000111 $
1'
#1287
0'
#1288
b000110 $
1'
#1289
0'
#1290
b000101 $
1'
#1291
0'
#1292
b000100 $
1'
#1293
0'
#1294
b000011 $
1'
#1295
0'
#1296
b000010 $
1'
#1297
0'
#1298
b000001 $
1'
#1299
0'
#1300
b000000 $
1'
#1301
0'
#1302
1#
b110101 $
1'
#1303
0'
#1304
0#
b110100 $
b00000000000000000000000000000011 %
b00000000000000000000000000000100 &
1'
b00000111 )
#1305
0'
#1306
b110011 $
1'
#1307
0'
#1308
b110010 $
1'
#1309
0'
#1310
b110001 $
1'
#1311
0'
#1312
b110000 $
1'
#1313
0'
#1314
b101111 $
1'
#1315
0'
#1316
b101110 $
1'
#1317
0'
#1318
b101101 $
1'
#1319
0'
#1320
b101100 $
1'
#1321
0'
#1322
b101011 $
1'
#1323
0'
#1324
b101010 $
1'
#1325
0'
#1326
b101001 $
1'
#1327
0'
#1328
b101000 $
1'
#1329
0'
#1330
b100111 $
1'
#1331
0'
#1332
b100110 $
1'
#1333
0'
#1334
b100101 $
1'
#1335
0'
#1336
b100100 $
1'
#1337
0'
#1338
b100011 $
1'
#1339
0'
#1340
b100010 $
1'
#1341
0'
#1342
b100001 $
1'
#1343
0'
#1344
b100000 $
1'
#1345
0'
#1346
b011111 $
1'
#1347
0'
#1348
b011110 $
1'
#1349
0'
#1350
b011101 $
1'
#1351
0'
#1352
b011100 $
1'
#1353
0'
#1354
b011011 $
1'
#1355
0'
#1356
b011010 $
1'
#1357
0'
#1358
b011001 $
1'
#1359
0'
#1360
b011000 $
1'
#1361
0'
